odoo10_addon_mass-10.0.1.0.1-py2.7-nspkg.pth
odoo/addons/mass/README.rst
odoo/addons/mass/__init__.py
odoo/addons/mass/__manifest__.py
odoo/addons/mass/base_config_settings.py
odoo/addons/mass/base_config_settings_view.xml
odoo/addons/mass/company.py
odoo/addons/mass/mass.py
odoo/addons/mass/mass_data.xml
odoo/addons/mass/mass_demo.xml
odoo/addons/mass/mass_view.xml
odoo/addons/mass/partner_view.xml
odoo/addons/mass/product_view.xml
odoo/addons/mass/report.xml
odoo/addons/mass/i18n/fr.po
odoo/addons/mass/security/ir.model.access.csv
odoo/addons/mass/security/mass_security.xml
odoo/addons/mass/static/description/icon.png
odoo/addons/mass/tests/__init__.py
odoo/addons/mass/tests/test_generate_mass_journal.py
odoo/addons/mass/views/report_massline.xml
odoo/addons/mass/views/report_massrequesttransfer.xml
odoo/addons/mass/wizard/__init__.py
odoo/addons/mass/wizard/generate_mass_journal.py
odoo/addons/mass/wizard/generate_mass_journal_view.xml
odoo/addons/mass/wizard/select_mass_requests_to_transfer.py
odoo/addons/mass/wizard/select_mass_requests_to_transfer_view.xml
odoo/addons/mass/wizard/swap_celebrant.py
odoo/addons/mass/wizard/swap_celebrant_view.xml
odoo/addons/mass/wizard/validate_mass_journal.py
odoo/addons/mass/wizard/validate_mass_journal_view.xml
odoo10_addon_mass-10.0.1.0.1.dist-info/METADATA
odoo10_addon_mass-10.0.1.0.1.dist-info/RECORD
odoo10_addon_mass-10.0.1.0.1.dist-info/WHEEL
odoo10_addon_mass-10.0.1.0.1.dist-info/namespace_packages.txt
odoo10_addon_mass-10.0.1.0.1.dist-info/top_level.txt
